{
  "repo": "/christianschmeing/eucorail-fleetops-demo",
  "branch": "main",
  "commit": {
    "sha": "259e1ed8ad054d5a010c62de9b746fca6f20fd1c",
    "message": "test: Add minimal HTML-only map test page\n\n- Pure server-side HTML, no JavaScript\n- Simple OpenStreetMap iframe\n- Test page at /depot/maptest\n- This MUST work - no client-side dependencies",
    "author": "Christian Schmeing",
    "timestamp": "2025-08-20T07:42:25Z"
  },
  "ci": {
    "status": "success",
    "workflow": "state",
    "run_id": "17091928268"
  },
  "changes": {
    "apps_web": false,
    "packages_api": false,
    "scripts": false,
    "docs": false
  },
  "issues": {
    "p0_open": 0,
    "p1_open": 0,
    "all_open": 0
  },
  "prs": {
    "open": 0
  },
  "data_version": null,
  "release": {
    "latest_tag": null
  },
  "generated_at": "2025-08-20T07:43:41.421Z",
  "default_branch_hint": "main",
  "agent_rules_url": "https://raw.githubusercontent.com/ChristianSchmeing/eucorail-fleetops-demo/main/docs/AGENT_SYSTEM_RULES.md",
  "agent_seed_url": "https://raw.githubusercontent.com/ChristianSchmeing/eucorail-fleetops-demo/main/.agent/SEED.prompt"
}